{"assets":{"B201F8059BCFA2195EDFCA7879948F50":{"type":"texture","index":3,"assetRequest":{"type":"slide","state":"contents","slide":"none"},"url":{"native":"assets\/5040AE6D-49AB-41B7-A4F2-B97CEB6257E2.pdf"},"width":720,"height":1280},"9B3C44640EBCB3D1204DF7E5AD5315E4":{"type":"texture","index":1,"assetRequest":{"type":"slide","state":"contents","slide":"none"},"url":{"native":"assets\/5040AE6D-49AB-41B7-A4F2-B97CEB6257E2.pdf"},"width":658,"height":351},"ACA21B525D278FCDF5F4F047878A681B":{"type":"texture","index":2,"assetRequest":{"type":"slide","state":"contents","slide":"none"},"url":{"native":"assets\/5040AE6D-49AB-41B7-A4F2-B97CEB6257E2.pdf"},"width":658,"height":927},"5A9C26C198A9D8EDFAB4DD87B315EC38":{"type":"texture","index":0,"assetRequest":{"type":"slide","state":"contents","slide":"none"},"url":{"native":"assets\/5040AE6D-49AB-41B7-A4F2-B97CEB6257E2.pdf"},"width":720,"height":1280},"DDC48494BFF4A1375C422E64C3DD51F3":{"type":"texture","index":4,"assetRequest":{"type":"slide","state":"contents","slide":"none"},"url":{"native":"assets\/5040AE6D-49AB-41B7-A4F2-B97CEB6257E2.pdf"},"width":720,"height":1280}},"events":[{"effects":[{"beginTime":0,"baseLayer":{"animations":[],"initialState":{"affineTransform":[1,0,0,1,0,0],"masksToBounds":false,"rotation":0,"scale":1,"position":{"pointX":361.48044204711914,"pointY":844.42304611206055},"width":658,"sublayerTransform":[1,0,0,0,0,1,0,0,0,0,1,0,0,0,0,1],"contentsRect":{"y":0,"x":0,"width":1,"height":1},"opacity":1,"edgeAntialiasingMask":251658240,"height":927,"hidden":false,"anchorPoint":{"pointX":0.5,"pointY":0.5}},"objectID":"D35088A1-9F25-4A59-8A3C-182777716478","layers":[{"animations":[],"initialState":{"affineTransform":[1,0,0,1,0,0],"masksToBounds":false,"rotation":0,"scale":1,"position":{"pointX":327.51955795288086,"pointY":259.07695388793945},"width":658,"sublayerTransform":[1,0,0,0,0,1,0,0,0,0,1,-0.0005251186870016398,0,0,0,1],"contentsRect":{"y":0,"x":0,"width":1,"height":1},"opacity":1,"edgeAntialiasingMask":251658240,"height":927,"hidden":false,"anchorPoint":{"pointX":0.497750088074287,"pointY":0.27947891465797137}},"layers":[{"animations":[{"timeOffset":0,"beginTime":1e-100,"repeatCount":0,"animations":[{"repeatCount":0,"timingControlPoint2y":0.76286590099334717,"from":{"pointX":327.51955795288086,"pointY":1364.5769538879395},"timingFunction":"custom","timeOffset":0,"autoreverses":false,"timingControlPoint1x":0.29938966035842896,"fillMode":"backwards","property":"position","duration":0.73750000000000004,"beginTime":0,"timingControlPoint2x":0.71488219499588013,"timingControlPoint1y":0.31214162707328796,"to":{"pointX":327.51955795288086,"pointY":437.11079957962033}},{"repeatCount":0,"timingControlPoint2y":1,"from":{"pointX":327.51955795288086,"pointY":437.11079957962033},"timingFunction":"custom","timeOffset":0,"autoreverses":false,"timingControlPoint1x":0.48835811018943787,"fillMode":"forwards","property":"position","duration":0.26249999999999996,"beginTime":0.73750000000000004,"timingControlPoint2x":0.62507688999176025,"timingControlPoint1y":0.96926283836364746,"to":{"pointX":327.51955795288086,"pointY":461.57695388793945}},{"timeOffset":0,"from":{"scalar":false},"beginTime":0,"repeatCount":0,"fillMode":"forwards","property":"hidden","autoreverses":false,"duration":1,"to":{"scalar":false}}],"fillMode":"both","autoreverses":false,"duration":1}],"layers":[],"texturedRectangle":{"singleTextureOpacity":1,"textXHeight":0,"shapePath":{"lineWidth":1,"flatness":0.59999999999999998,"lineCapStyle":0,"elements":[{"type":"MoveToPoint","points":[[1.4804420471191406,1.9230461120605469]]},{"type":"AddLine","points":[[656.51956176757812,1.9230461120605469]]},{"type":"AddLine","points":[[656.51956176757812,925.90776443481445]]},{"type":"AddLine","points":[[1.4804420471191406,925.90776443481445]]},{"type":"CloseSubpath"},{"type":"MoveToPoint","points":[[1.4804420471191406,1.9230461120605469]]}],"windingRule":0,"lineJoinStyle":0,"miterLimit":10},"isBackgroundTexture":true,"textBaseline":0,"isVerticalText":false,"textureType":5},"initialState":{"affineTransform":[1,0,0,1,0,0],"masksToBounds":false,"rotation":0,"scale":1,"position":{"pointX":327.51955795288086,"pointY":461.57695388793945},"width":658,"sublayerTransform":[1,0,0,0,0,1,0,0,0,0,1,0,0,0,0,1],"contentsRect":{"y":0,"x":0,"width":1,"height":1},"opacity":1,"edgeAntialiasingMask":0,"height":927,"hidden":true,"anchorPoint":{"pointX":0.5,"pointY":0.5}},"texture":"ACA21B525D278FCDF5F4F047878A681B"}]}]},"effects":[],"duration":1,"type":"buildIn","attributes":{"direction":14},"name":"apple:move in character","objectID":"D35088A1-9F25-4A59-8A3C-182777716478"}],"automaticPlay":false,"hyperlinks":[],"accessibility":[{"text":"There were many similarities between the two treaties. However, there were also some important differences.","targetRectangle":{"y":58.6726975440979,"x":58.141441345214844,"width":603.71710205078216,"height":306.00001215934753}}],"baseLayer":{"animations":[],"initialState":{"affineTransform":[1,0,0,1,0,0],"masksToBounds":false,"rotation":0,"scale":1,"position":{"pointX":360,"pointY":640},"width":720,"sublayerTransform":[1,0,0,0,0,1,0,0,0,0,1,0,0,0,0,1],"contentsRect":{"y":0,"x":0,"width":1,"height":1},"opacity":1,"edgeAntialiasingMask":251658240,"height":1280,"hidden":false,"anchorPoint":{"pointX":0.5,"pointY":0.5}},"layers":[{"animations":[],"initialState":{"affineTransform":[1,0,0,1,0,0],"masksToBounds":false,"rotation":0,"scale":1,"position":{"pointX":360,"pointY":640},"width":720,"sublayerTransform":[1,0,0,0,0,1,0,0,0,0,1,0,0,0,0,1],"contentsRect":{"y":0,"x":0,"width":1,"height":1},"opacity":1,"edgeAntialiasingMask":251658240,"height":1280,"hidden":false,"anchorPoint":{"pointX":0.5,"pointY":0.5}},"layers":[{"animations":[],"initialState":{"affineTransform":[1,0,0,1,0,0],"masksToBounds":false,"rotation":0,"scale":1,"position":{"pointX":360,"pointY":640},"width":720,"sublayerTransform":[1,0,0,0,0,1,0,0,0,0,1,0,0,0,0,1],"contentsRect":{"y":0,"x":0,"width":1,"height":1},"opacity":1,"edgeAntialiasingMask":251658240,"height":1280,"hidden":false,"anchorPoint":{"pointX":0.5,"pointY":0.5}},"layers":[{"animations":[],"layers":[],"texturedRectangle":{"isBackgroundTexture":true,"singleTextureOpacity":1,"textureType":1,"textBaseline":0,"textXHeight":0,"isVerticalText":false},"initialState":{"affineTransform":[1,0,0,1,0,0],"masksToBounds":false,"rotation":0,"scale":1,"position":{"pointX":360,"pointY":640},"width":720,"sublayerTransform":[1,0,0,0,0,1,0,0,0,0,1,0,0,0,0,1],"contentsRect":{"y":0,"x":0,"width":1,"height":1},"opacity":1,"edgeAntialiasingMask":0,"height":1280,"hidden":false,"anchorPoint":{"pointX":0.5,"pointY":0.5}},"texture":"5A9C26C198A9D8EDFAB4DD87B315EC38"}]}]},{"animations":[],"initialState":{"affineTransform":[1,0,0,1,0,0],"masksToBounds":false,"rotation":0,"scale":1,"position":{"pointX":360,"pointY":640},"width":720,"sublayerTransform":[1,0,0,0,0,1,0,0,0,0,1,0,0,0,0,1],"contentsRect":{"y":0,"x":0,"width":1,"height":1},"opacity":1,"edgeAntialiasingMask":251658240,"height":1280,"hidden":false,"anchorPoint":{"pointX":0.5,"pointY":0.5}},"layers":[{"animations":[],"initialState":{"affineTransform":[1,0,0,1,0,0],"masksToBounds":false,"rotation":0,"scale":1,"position":{"pointX":361.14144134521484,"pointY":208.1726975440979},"width":658,"sublayerTransform":[1,0,0,0,0,1,0,0,0,0,1,0,0,0,0,1],"contentsRect":{"y":0,"x":0,"width":1,"height":1},"opacity":1,"edgeAntialiasingMask":251658240,"height":351,"hidden":false,"anchorPoint":{"pointX":0.5,"pointY":0.5}},"layers":[{"animations":[],"layers":[],"texturedRectangle":{"singleTextureOpacity":1,"textXHeight":0,"shapePath":{"lineWidth":1,"flatness":0.59999999999999998,"lineCapStyle":0,"elements":[{"type":"MoveToPoint","points":[[3.6414413452148438,4.1726975440979004]]},{"type":"AddLine","points":[[654.35855674743652,4.1726975440979004]]},{"type":"AddLine","points":[[654.35855674743652,346.97271871566772]]},{"type":"AddLine","points":[[3.6414413452148438,346.97271871566772]]},{"type":"CloseSubpath"},{"type":"MoveToPoint","points":[[3.6414413452148438,4.1726975440979004]]}],"windingRule":0,"lineJoinStyle":0,"miterLimit":10},"isBackgroundTexture":true,"textBaseline":0,"isVerticalText":false,"textureType":5},"initialState":{"affineTransform":[1,0,0,1,0,0],"masksToBounds":false,"rotation":0,"scale":1,"position":{"pointX":327.85855865478516,"pointY":173.8273024559021},"width":658,"sublayerTransform":[1,0,0,0,0,1,0,0,0,0,1,0,0,0,0,1],"contentsRect":{"y":0,"x":0,"width":1,"height":1},"opacity":1,"edgeAntialiasingMask":0,"height":351,"hidden":false,"anchorPoint":{"pointX":0.5,"pointY":0.5}},"texture":"9B3C44640EBCB3D1204DF7E5AD5315E4"}]}]},{"animations":[],"initialState":{"affineTransform":[1,0,0,1,0,0],"masksToBounds":false,"rotation":0,"scale":1,"position":{"pointX":360,"pointY":640},"width":720,"sublayerTransform":[1,0,0,0,0,1,0,0,0,0,1,0,0,0,0,1],"contentsRect":{"y":0,"x":0,"width":1,"height":1},"opacity":1,"edgeAntialiasingMask":251658240,"height":1280,"hidden":false,"anchorPoint":{"pointX":0.5,"pointY":0.5}},"layers":[{"animations":[],"initialState":{"affineTransform":[1,0,0,1,0,0],"masksToBounds":false,"rotation":0,"scale":1,"position":{"pointX":361.48044204711914,"pointY":844.42304611206055},"width":658,"sublayerTransform":[1,0,0,0,0,1,0,0,0,0,1,0,0,0,0,1],"contentsRect":{"y":0,"x":0,"width":1,"height":1},"opacity":1,"edgeAntialiasingMask":251658240,"height":927,"hidden":false,"anchorPoint":{"pointX":0.5,"pointY":0.5}},"objectID":"D35088A1-9F25-4A59-8A3C-182777716478","layers":[{"animations":[],"layers":[],"texturedRectangle":{"singleTextureOpacity":1,"textXHeight":0,"shapePath":{"lineWidth":1,"flatness":0.59999999999999998,"lineCapStyle":0,"elements":[{"type":"MoveToPoint","points":[[1.4804420471191406,1.9230461120605469]]},{"type":"AddLine","points":[[656.51956176757812,1.9230461120605469]]},{"type":"AddLine","points":[[656.51956176757812,925.90776443481445]]},{"type":"AddLine","points":[[1.4804420471191406,925.90776443481445]]},{"type":"CloseSubpath"},{"type":"MoveToPoint","points":[[1.4804420471191406,1.9230461120605469]]}],"windingRule":0,"lineJoinStyle":0,"miterLimit":10},"isBackgroundTexture":true,"textBaseline":0,"isVerticalText":false,"textureType":5},"initialState":{"affineTransform":[1,0,0,1,0,0],"masksToBounds":false,"rotation":0,"scale":1,"position":{"pointX":327.51955795288086,"pointY":461.57695388793945},"width":658,"sublayerTransform":[1,0,0,0,0,1,0,0,0,0,1,0,0,0,0,1],"contentsRect":{"y":0,"x":0,"width":1,"height":1},"opacity":1,"edgeAntialiasingMask":0,"height":927,"hidden":true,"anchorPoint":{"pointX":0.5,"pointY":0.5}},"texture":"ACA21B525D278FCDF5F4F047878A681B"}]}]}]}},{"effects":[{"beginTime":0,"baseLayer":{"animations":[],"initialState":{"affineTransform":[1,0,0,1,0,0],"masksToBounds":false,"rotation":0,"scale":1,"position":{"pointX":360,"pointY":640},"width":720,"sublayerTransform":[1,0,0,0,0,1,0,0,0,0,1,0,0,0,0,1],"contentsRect":{"y":0,"x":0,"width":1,"height":1},"opacity":1,"edgeAntialiasingMask":251658240,"height":1280,"hidden":false,"anchorPoint":{"pointX":0.5,"pointY":0.5}},"objectID":"0","layers":[{"animations":[],"initialState":{"affineTransform":[1,0,0,1,0,0],"masksToBounds":false,"rotation":0,"scale":1,"position":{"pointX":360,"pointY":640},"width":720,"sublayerTransform":[1,0,0,0,0,1,0,0,0,0,1,-0.0005251186870016398,0,0,0,1],"contentsRect":{"y":0,"x":0,"width":1,"height":1},"opacity":1,"edgeAntialiasingMask":251658240,"height":1280,"hidden":false,"anchorPoint":{"pointX":0.5,"pointY":0.5}},"layers":[{"animations":[],"layers":[],"texturedRectangle":{"isBackgroundTexture":false,"singleTextureOpacity":1,"textureType":0,"textBaseline":0,"textXHeight":0,"isVerticalText":false},"initialState":{"affineTransform":[1,0,0,1,0,0],"masksToBounds":false,"rotation":0,"scale":1,"position":{"pointX":360,"pointY":640},"width":720,"sublayerTransform":[1,0,0,0,0,1,0,0,0,0,1,0,0,0,0,1],"contentsRect":{"y":0,"x":0,"width":1,"height":1},"opacity":1,"edgeAntialiasingMask":0,"height":1280,"hidden":false,"anchorPoint":{"pointX":0.5,"pointY":0.5}},"texture":"DDC48494BFF4A1375C422E64C3DD51F3"},{"animations":[{"timeOffset":0,"from":{"scalar":false},"beginTime":0,"repeatCount":0,"fillMode":"both","property":"hidden","autoreverses":false,"duration":0.01,"to":{"scalar":true}}],"layers":[],"texturedRectangle":{"isBackgroundTexture":false,"singleTextureOpacity":1,"textureType":0,"textBaseline":0,"textXHeight":0,"isVerticalText":false},"initialState":{"affineTransform":[1,0,0,1,0,0],"masksToBounds":false,"rotation":0,"scale":1,"position":{"pointX":360,"pointY":640},"width":720,"sublayerTransform":[1,0,0,0,0,1,0,0,0,0,1,0,0,0,0,1],"contentsRect":{"y":0,"x":0,"width":1,"height":1},"opacity":1,"edgeAntialiasingMask":0,"height":1280,"hidden":false,"anchorPoint":{"pointX":0.5,"pointY":0.5}},"texture":"B201F8059BCFA2195EDFCA7879948F50"}]}]},"effects":[],"duration":0.01,"type":"transition","attributes":{"direction":0},"name":"none","objectID":"0"}],"automaticPlay":false,"hyperlinks":[],"accessibility":[{"text":"There were many similarities between the two treaties. However, there were also some important differences.","targetRectangle":{"y":58.6726975440979,"x":58.141441345214844,"width":603.71710205078216,"height":306.00001215934753}},{"text":" ","targetRectangle":{"y":401.92304611206055,"x":53.480442047119141,"width":9.730000000000004,"height":40.984756469726562}},{"text":"SUPER POWERS","targetRectangle":{"y":443.92304611206055,"x":212.45750381469728,"width":295.08500000000004,"height":43}},{"text":" ","targetRectangle":{"y":486.92304611206055,"x":53.480442047119141,"width":9.730000000000004,"height":40.984756469726562}},{"text":"The Great War left all the Great Powers badly wounded. No new power emerged between the wars.","targetRectangle":{"y":528.92304611206055,"x":53.480442047119141,"width":613.03912353515591,"height":124.98475646972656}},{"text":" ","targetRectangle":{"y":654.92304611206055,"x":53.480442047119141,"width":9.730000000000004,"height":40.984756469726562}},{"text":"By 1945 it was obvious that two countries had become Super Powers. These were the U.S.A. and the U.S.S.R. They had massive military capability. Between them, they occupied most of what had been Nazi Europe. This caused tension at the the peace conferences.","targetRectangle":{"y":696.92304611206055,"x":53.480442047119141,"width":613.03912353515693,"height":334.98475646972656}},{"text":" ","targetRectangle":{"y":1032.9230461120605,"x":53.480442047119141,"width":9.730000000000004,"height":40.984756469726562}},{"text":"Later differences emerged between the U.S.S.R over the Germany and the use of atomic weapons. This lead to the Cold War.","targetRectangle":{"y":1074.9230461120605,"x":53.480442047119141,"width":613.03912353515625,"height":166.98475646972656}}],"baseLayer":{"animations":[],"initialState":{"affineTransform":[1,0,0,1,0,0],"masksToBounds":false,"rotation":0,"scale":1,"position":{"pointX":360,"pointY":640},"width":720,"sublayerTransform":[1,0,0,0,0,1,0,0,0,0,1,0,0,0,0,1],"contentsRect":{"y":0,"x":0,"width":1,"height":1},"opacity":1,"edgeAntialiasingMask":251658240,"height":1280,"hidden":false,"anchorPoint":{"pointX":0.5,"pointY":0.5}},"objectID":"0","layers":[{"animations":[],"initialState":{"affineTransform":[1,0,0,1,0,0],"masksToBounds":false,"rotation":0,"scale":1,"position":{"pointX":360,"pointY":640},"width":720,"sublayerTransform":[1,0,0,0,0,1,0,0,0,0,1,-0.0005251186870016398,0,0,0,1],"contentsRect":{"y":0,"x":0,"width":1,"height":1},"opacity":1,"edgeAntialiasingMask":251658240,"height":1280,"hidden":false,"anchorPoint":{"pointX":0.5,"pointY":0.5}},"layers":[{"animations":[],"layers":[],"texturedRectangle":{"isBackgroundTexture":false,"singleTextureOpacity":1,"textureType":0,"textBaseline":0,"textXHeight":0,"isVerticalText":false},"initialState":{"affineTransform":[1,0,0,1,0,0],"masksToBounds":false,"rotation":0,"scale":1,"position":{"pointX":360,"pointY":640},"width":720,"sublayerTransform":[1,0,0,0,0,1,0,0,0,0,1,0,0,0,0,1],"contentsRect":{"y":0,"x":0,"width":1,"height":1},"opacity":1,"edgeAntialiasingMask":0,"height":1280,"hidden":false,"anchorPoint":{"pointX":0.5,"pointY":0.5}},"texture":"B201F8059BCFA2195EDFCA7879948F50"}]}]}}]}